<order id="1"><customer ref="c2" /><operation id="1.wheelpair.1" ref="shaftwheelassemble"><operation id="1.wheelpair.1.1" ref="shaftwheelassemble"><material id="1.wheelpair.1.1.shaft" ref="shaft"><operation id="1.wheelpair.1.1.shaft.1" ref="shaftprocessing"><material id="1.wheelpair.1.1.shaft.1.1" ref="blankshaft"><operation id="1.wheelpair.1.1.shaft.1.1.1" ref="orderblankshaft"><operation id="1.wheelpair.1.1.shaft.1.1.1.bookblankshaft" ref="bookblankshaft" /><operation id="1.wheelpair.1.1.shaft.1.1.1.2" ref="deliverytocwh" /></operation></material></operation></material><material id="1.wheelpair.1.1.wheel1" ref="wheel"><operation id="1.wheelpair.1.1.wheel1.1" ref="supplierselection" /><operation id="1.wheelpair.1.1.wheel1.2" ref="suppliercontraction" /><operation id="1.wheelpair.1.1.wheel1.3" ref="deliverytocwh" /></material></operation><material id="1.wheelpair.1.wheel2" ref="wheel"><operation id="1.wheelpair.1.wheel2.1" ref="supplierselection" /><operation id="1.wheelpair.1.wheel2.2" ref="suppliercontraction" /><operation id="1.wheelpair.1.wheel2.3" ref="deliverytocwh" /></material></operation><operation id="1.wheelpair.transtoqc" ref="transportinws1" /><operation id="1.wheelpair.qc" ref="qualitycheck" /><operation id="1.wheelpair.transtofwh" ref="transportinws1" /></order>