<routes orderref="o-127"><route id="o-127.1" workcenter="wc2_4"><product ref="o-127.1.wheelpair" refref="wheelpair"><operation ref="o-127.1.wheelpair.1" refref="qualitycheck" workcenter="wc2_4"><operation ref="o-127.1.wheelpair.1.1" refref="wheelpairassemble" workcenter="wc2_3"><material ref="o-127.1.wheelpair.1.1.shaft" refref="shaft"><operation ref="o-127.1.wheelpair.1.1.shaft.1" refref="blankprocessing" workcenter="wc1_3"><material ref="o-127.1.wheelpair.1.1.shaft.1.1" refref="blankshaft"><operation ref="o-127.1.wheelpair.1.1.shaft.1.1.1" refref="supplyblankshaft" workcenter="wc1_1" /></material></operation></material><material ref="o-127.1.wheelpair.1.1.wheel" refref="wheel"><operation ref="o-127.1.wheelpair.1.1.wheel.1" refref="supplywheel" workcenter="wc2_1" /></material></operation></operation></product></route></routes>